code_analyzer/__init__.py
code_analyzer/__main__.py
code_analyzer/__version__.py
code_analyzer/analyzers/__init__.py
code_analyzer/analyzers/bigquery_analyzer.py
code_analyzer/analyzers/db2_analyzer.py
code_analyzer/analyzers/mysql_analyzer.py
code_analyzer/analyzers/oracle_analyzer.py
code_analyzer/analyzers/postgresql_analyzer.py
code_analyzer/analyzers/pyspark_analyzer.py
code_analyzer/analyzers/python_analyzer.py
code_analyzer/analyzers/redshift_analyzer.py
code_analyzer/analyzers/sas_analyzer.py
code_analyzer/analyzers/snowsql_analyzer.py
code_analyzer/analyzers/sparksql_analyzer.py
code_analyzer/analyzers/sqlite_analyzer.py
code_analyzer/analyzers/sqlserver_analyzer.py
code_analyzer/analyzers/sybase_analyzer.py
code_analyzer/cli.py
code_analyzer/config/__init__.py
code_analyzer/config/defaults/__init__.py
code_analyzer/config/defaults/config.yaml
code_analyzer/config/loader.py
code_analyzer/core/__init__.py
code_analyzer/core/analyzer_base.py
code_analyzer/core/exception.py
code_analyzer/core/metrics.py
code_analyzer/core/registry.py
code_analyzer/reporters/__init__.py
code_analyzer/utils/__init__.py
pyspcodeanalyzer-1.0.0.dist-info/entry_points.txt
pyspcodeanalyzer-1.0.0.dist-info/licenses/LICENSE
pyspcodeanalyzer-1.0.0.dist-info/METADATA
pyspcodeanalyzer-1.0.0.dist-info/WHEEL
pyspcodeanalyzer-1.0.0.dist-info/RECORD
