Metadata-Version: 2.4
Name: pyspcodeanalyzer
Version: 1.0.0
Summary: Enterprise-grade code complexity analyzer supporting mutiple programming languages with standardized metrics.
License: MIT
License-File: LICENSE
Keywords: code analysis,complexity,metrics,sql,python,sas,static analysis,code quality,enterprise,technical debt
Author: Gefin R Samuel
Maintainer: Code Analyzer Team
Maintainer-email: support@codeanalyzer.dev
Requires-Python: >=3.8.1,<4.0.0
Classifier: Development Status :: 5 - Production/Stable
Classifier: Intended Audience :: Developers
Classifier: Intended Audience :: Information Technology
Classifier: License :: OSI Approved :: MIT License
Classifier: Operating System :: OS Independent
Classifier: Programming Language :: Python :: 3
Classifier: Programming Language :: Python :: 3.9
Classifier: Programming Language :: Python :: 3.10
Classifier: Programming Language :: Python :: 3.11
Classifier: Programming Language :: Python :: 3.12
Classifier: Programming Language :: Python :: 3.13
Classifier: Programming Language :: Python :: 3.14
Classifier: Programming Language :: Python :: 3.8
Classifier: Topic :: Database
Classifier: Topic :: Scientific/Engineering :: Information Analysis
Classifier: Topic :: Software Development :: Libraries :: Python Modules
Classifier: Topic :: Software Development :: Quality Assurance
Requires-Dist: click (>=8.0.0,<9.0.0)
Requires-Dist: pyyaml (>=6.0,<7.0)
Project-URL: Documentation, https://code-analyzer.readthedocs.io
Project-URL: Homepage, https://github.com/codeanalyzer/code-analyzer
Project-URL: Repository, https://github.com/codeanalyzer/code-analyzer
